gcloud_aio_pubsub_rpc/__init__.py
gcloud_aio_pubsub_rpc/config.py
gcloud_aio_pubsub_rpc/ordered_stream.py
gcloud_aio_pubsub_rpc/pubsub_clients.py
gcloud_aio_pubsub_rpc/push_pubsub_message.py
gcloud_aio_pubsub_rpc/rpc.py
gcloud_aio_pubsub_rpc-0.1.1.dist-info/LICENSE
gcloud_aio_pubsub_rpc-0.1.1.dist-info/METADATA
gcloud_aio_pubsub_rpc-0.1.1.dist-info/WHEEL
gcloud_aio_pubsub_rpc-0.1.1.dist-info/RECORD
